pygellan/__init__.py
pygellan/acquire.py
pygellan/magellan_data.py
pygellan-0.2.0.dist-info/LICENSE
pygellan-0.2.0.dist-info/METADATA
pygellan-0.2.0.dist-info/WHEEL
pygellan-0.2.0.dist-info/top_level.txt
pygellan-0.2.0.dist-info/RECORD
