Metadata-Version: 2.1
Name: pygellan
Version: 0.2.0
Summary: Open source microscope control using python
Home-page: https://github.com/henrypinkard/Pygellan
Author: Henry Pinkard
Author-email: henry.pinkard@gmail.com
License: UNKNOWN
Platform: UNKNOWN
Classifier: Programming Language :: Python :: 3
Classifier: Development Status :: 3 - Alpha
Classifier: License :: OSI Approved :: BSD License
Classifier: Operating System :: OS Independent
Requires-Dist: numpy
Requires-Dist: dask[array] (>=2.4.0)
Requires-Dist: zmq
